spline_resize/__init__.py
spline_resize/main.py
spline_resize/utils.py
spline_resize-0.1.1.dist-info/LICENSE
spline_resize-0.1.1.dist-info/METADATA
spline_resize-0.1.1.dist-info/WHEEL
spline_resize-0.1.1.dist-info/RECORD
